pframe/__init__.py
pframe/version.py
pframe/container/__init__.py
pframe/container/pdatetime.py
pframe/container/plist.py
pframe/container/pobject.py
pframe/container/ptime.py
pframe/crypto/__init__.py
pframe/crypto/pmd5.py
pframe/crypto/pseed.py
pframe/encoding/__init__.py
pframe/encoding/pjson.py
pframe/system/__init__.py
pframe/system/platform.py
pframe/util/__init__.py
pframe/util/exception.py
pframe-20200310.1.dist-info/LICENSE
pframe-20200310.1.dist-info/METADATA
pframe-20200310.1.dist-info/WHEEL
pframe-20200310.1.dist-info/top_level.txt
pframe-20200310.1.dist-info/RECORD
