Metadata-Version: 2.1
Name: pframe
Version: 20200310.1
Summary: PFrame is a basic framework for python
Home-page: https://github.com/Eastwu5788/PFrame
Author: LeonardWoo
Author-email: wudong@eastwu.cn
License: MIT
Platform: UNKNOWN
Classifier: License :: OSI Approved :: MIT License
Classifier: Programming Language :: Python
Classifier: Programming Language :: Python :: 3
Classifier: Programming Language :: Python :: 3.6
Classifier: Programming Language :: Python :: Implementation :: CPython
Classifier: Programming Language :: Python :: Implementation :: PyPy
Requires-Python: ~=3.2
